AUTHORS
LICENSE
MANIFEST.in
README.md
setup.py
biplist/__init__.py
biplist.egg-info/PKG-INFO
biplist.egg-info/SOURCES.txt
biplist.egg-info/dependency_links.txt
biplist.egg-info/not-zip-safe
biplist.egg-info/requires.txt
biplist.egg-info/top_level.txt
tests/test_invalid.py
tests/test_utils.py
tests/test_valid.py
tests/test_write.py
tests/data/array_only_binary.plist
tests/data/bogus_file.plist
tests/data/bool_only_binary.plist
tests/data/dict_only_binary.plist
tests/data/empty_file.plist
tests/data/large_int_limits.plist
tests/data/nskeyedarchiver_example.plist
tests/data/simple_binary.plist
tests/data/small_real.plist
tests/data/unicode_empty.plist
tests/data/unicode_root.plist