Metadata-Version: 1.1
Name: biplist
Version: 0.8
Summary: biplist is a library for reading/writing binary plists.
Home-page: https://bitbucket.org/wooster/biplist
Author: Andrew Wooster
Author-email: andrew@planetaryscale.com
License: BSD
Download-URL: https://bitbucket.org/wooster/biplist/downloads/biplist-0.8.tar.gz
Platform: UNKNOWN
Classifier: Development Status :: 5 - Production/Stable
Classifier: Intended Audience :: Developers
Classifier: License :: OSI Approved :: BSD License
Classifier: Operating System :: OS Independent
Classifier: Programming Language :: Python
Classifier: Topic :: Software Development :: Libraries :: Python Modules
Classifier: Topic :: Text Processing :: Markup
Requires: six
